src/hyperDS/__init__.py
src/hyperDS/exceptions.py
src/hyperDS/updater.py
src/hyperDS/utils.py
hyperDataS-1.0.0.dist-info/METADATA
hyperDataS-1.0.0.dist-info/WHEEL
hyperDataS-1.0.0.dist-info/top_level.txt
hyperDataS-1.0.0.dist-info/RECORD
