Metadata-Version: 2.1
Name: hyperDataS
Version: 1.0.0
Summary: hyperDataS (stands for HyperDataStorage) is a library written in Python used to store/retrieve complex data
Home-page: https://github.com/AbdulWahab321/HyperDS
Author: AbdulWahab
Author-email: jr.abdulwahab@gmail.com
License: UNKNOWN
Platform: UNKNOWN
Classifier: Development Status :: 5 - Production/Stable
Classifier: Intended Audience :: Developers
Classifier: License :: OSI Approved :: MIT License
Classifier: Programming Language :: Python :: 3
Requires-Python: >=3
Requires-Dist: pyzipper
